notas_musicais/__init__.py
notas_musicais/acordes.py
notas_musicais/campo_harmonico.py
notas_musicais/cli.py
notas_musicais/escalas.py
notas_musicais_hcca-0.1.0.dist-info/METADATA
notas_musicais_hcca-0.1.0.dist-info/WHEEL
notas_musicais_hcca-0.1.0.dist-info/entry_points.txt
notas_musicais_hcca-0.1.0.dist-info/RECORD
